airtouch/__init__.py
airtouch-0.0.1.dist-info/LICENSE
airtouch-0.0.1.dist-info/METADATA
airtouch-0.0.1.dist-info/WHEEL
airtouch-0.0.1.dist-info/top_level.txt
airtouch-0.0.1.dist-info/RECORD
