Metadata-Version: 2.1
Name: airtouch
Version: 0.0.1
Summary: A library for Polyaire Airtouch controllers
Home-page: https://github.com/some-guy-in-oz/airtouch
Author: Some Guy in Oz
Author-email: someguyoz99@gmail.com
License: UNKNOWN
Project-URL: Bug Tracker, https://github.com/some-guy-in-oz/airtouch/issues
Platform: UNKNOWN
Classifier: Programming Language :: Python :: 3
Classifier: License :: OSI Approved :: MIT License
Classifier: Operating System :: OS Independent
Requires-Python: >=3.6
License-File: LICENSE
